LiangxingGoudaZhinanX6/README.md
LiangxingGoudaZhinanX6/__init__.py
LiangxingGoudaZhinanX6/__main__.py
LiangxingGoudaZhinanX6/file.epub
LiangxingGoudaZhinanX6/index.html
LiangxingGoudaZhinanX6/css/__init__.py
LiangxingGoudaZhinanX6/css/annotations.css
LiangxingGoudaZhinanX6/css/main.css
LiangxingGoudaZhinanX6/css/normalize.css
LiangxingGoudaZhinanX6/css/popup.css
LiangxingGoudaZhinanX6/font/__init__.py
LiangxingGoudaZhinanX6/font/fontello.eot
LiangxingGoudaZhinanX6/font/fontello.svg
LiangxingGoudaZhinanX6/font/fontello.ttf
LiangxingGoudaZhinanX6/font/fontello.woff
LiangxingGoudaZhinanX6/img/__init__.py
LiangxingGoudaZhinanX6/img/annotator-glyph-sprite.png
LiangxingGoudaZhinanX6/img/annotator-icon-sprite.png
LiangxingGoudaZhinanX6/img/apple-touch-icon.png
LiangxingGoudaZhinanX6/img/cancelfullscreen.png
LiangxingGoudaZhinanX6/img/close.png
LiangxingGoudaZhinanX6/img/fullscreen.png
LiangxingGoudaZhinanX6/img/loader.gif
LiangxingGoudaZhinanX6/img/menu-icon.png
LiangxingGoudaZhinanX6/img/save.png
LiangxingGoudaZhinanX6/img/saved.png
LiangxingGoudaZhinanX6/img/settings-s.png
LiangxingGoudaZhinanX6/img/settings.png
LiangxingGoudaZhinanX6/img/star.png
LiangxingGoudaZhinanX6/js/__init__.py
LiangxingGoudaZhinanX6/js/epub.js
LiangxingGoudaZhinanX6/js/epub.min.js
LiangxingGoudaZhinanX6/js/epub.min.map
LiangxingGoudaZhinanX6/js/hooks.min.js
LiangxingGoudaZhinanX6/js/hooks.min.map
LiangxingGoudaZhinanX6/js/reader.js
LiangxingGoudaZhinanX6/js/reader.js.map
LiangxingGoudaZhinanX6/js/reader.min.js
LiangxingGoudaZhinanX6/js/reader.min.map
LiangxingGoudaZhinanX6/js/hooks/__init__.py
LiangxingGoudaZhinanX6/js/hooks/extensions/__init__.py
LiangxingGoudaZhinanX6/js/hooks/extensions/highlight.js
LiangxingGoudaZhinanX6/js/libs/__init__.py
LiangxingGoudaZhinanX6/js/libs/jquery.min.js
LiangxingGoudaZhinanX6/js/libs/localforage.min.js
LiangxingGoudaZhinanX6/js/libs/screenfull.js
LiangxingGoudaZhinanX6/js/libs/screenfull.min.js
LiangxingGoudaZhinanX6/js/libs/zip.min.js
liangxing_gouda_zhinan_x6-2022.10.11.0.dist-info/METADATA
liangxing_gouda_zhinan_x6-2022.10.11.0.dist-info/WHEEL
liangxing_gouda_zhinan_x6-2022.10.11.0.dist-info/entry_points.txt
liangxing_gouda_zhinan_x6-2022.10.11.0.dist-info/top_level.txt
liangxing_gouda_zhinan_x6-2022.10.11.0.dist-info/RECORD
